spoken_time/__init__.py
spoken_time/locale/spoken_time.pot
spoken_time/locale/de/LC_MESSAGES/spoken_time.mo
spoken_time/locale/de/LC_MESSAGES/spoken_time.po
spoken_time-0.1.0.dist-info/LICENSE.txt
spoken_time-0.1.0.dist-info/METADATA
spoken_time-0.1.0.dist-info/WHEEL
spoken_time-0.1.0.dist-info/top_level.txt
spoken_time-0.1.0.dist-info/RECORD
