Metadata-Version: 2.1
Name: spoken-time
Version: 0.1.0
Summary: Format dates and times for TTS
Home-page: https://github.com/dnknth/spoken_time
Author: dnknth
License: UNKNOWN
Platform: UNKNOWN
Classifier: License :: OSI Approved :: MIT License
Classifier: Operating System :: OS Independent
Classifier: Development Status :: 3 - Alpha
Classifier: Intended Audience :: Developers
Classifier: Programming Language :: Python :: 3 :: Only
Classifier: Topic :: Software Development :: Libraries
License-File: LICENSE.txt
Requires-Dist: setuptools
Requires-Dist: num2words (==0.5.*)
